luxin/__init__.py
luxin/display.py
luxin/drill_table.py
luxin/jupyter_backend.py
luxin/streamlit_backend.py
luxin/tracked_df.py
luxin/static/table.css
luxin/static/table.js
luxin/templates/table.html
luxin-0.1.0.dist-info/licenses/LICENSE
luxin-0.1.0.dist-info/METADATA
luxin-0.1.0.dist-info/WHEEL
luxin-0.1.0.dist-info/top_level.txt
luxin-0.1.0.dist-info/RECORD
