Metadata-Version: 2.4
Name: luxin
Version: 0.1.0
Summary: Interactive HTML tables with drill-down capabilities for exploring aggregated data
Author-email: Odos Matthews <odosmatthews@gmail.com>
License: MIT
Project-URL: Repository, https://github.com/eddiethedean/luxin
Project-URL: Homepage, https://github.com/eddiethedean/luxin
Project-URL: Bug Tracker, https://github.com/eddiethedean/luxin/issues
Keywords: dataframe,visualization,jupyter,streamlit,interactive,drill-down
Classifier: Development Status :: 4 - Beta
Classifier: Intended Audience :: Developers
Classifier: Intended Audience :: Science/Research
Classifier: Programming Language :: Python :: 3
Classifier: Programming Language :: Python :: 3.8
Classifier: Programming Language :: Python :: 3.9
Classifier: Programming Language :: Python :: 3.10
Classifier: Programming Language :: Python :: 3.11
Classifier: Programming Language :: Python :: 3.12
Classifier: Topic :: Scientific/Engineering :: Visualization
Classifier: Topic :: Software Development :: Libraries :: Python Modules
Classifier: Framework :: Jupyter
Requires-Python: >=3.8
License-File: LICENSE
Requires-Dist: pandas>=1.3.0
Requires-Dist: ipython>=7.0.0
Provides-Extra: polars
Requires-Dist: polars>=0.20.0; extra == "polars"
Provides-Extra: streamlit
Requires-Dist: streamlit>=1.0.0; extra == "streamlit"
Provides-Extra: dev
Requires-Dist: pytest>=7.0.0; extra == "dev"
Requires-Dist: pytest-cov>=4.0.0; extra == "dev"
Requires-Dist: jupyter>=1.0.0; extra == "dev"
Requires-Dist: notebook>=6.0.0; extra == "dev"
Dynamic: license-file
